itera_lib/__init__.py
itera_lib/cli.py
itera_lib/graphrag.py
itera-0.6.0.dist-info/LICENSE
itera-0.6.0.dist-info/METADATA
itera-0.6.0.dist-info/WHEEL
itera-0.6.0.dist-info/entry_points.txt
itera-0.6.0.dist-info/top_level.txt
itera-0.6.0.dist-info/RECORD
